Func2DCad/__init__.py
Func2DCad/solution_task1.py
Func2DCad/solution_task2.py
Func2DCad/solution_task3.py
Func2DCad/solution_task4.py
Func2DCad/solution_task5.py
Func2DCad/solution_task6.py
Func2DCad/solution_task7.py
Func2DCad/solution_task8.py
Func2DCad/solution_task9.py
Func2DCad/ssh_config.py
func2dcad-1.3.2.dist-info/METADATA
func2dcad-1.3.2.dist-info/WHEEL
func2dcad-1.3.2.dist-info/top_level.txt
func2dcad-1.3.2.dist-info/RECORD
