Metadata-Version: 2.4
Name: Func2DCad
Version: 1.3.2
Summary: HTTP library with thread-safe connection pooling, file post, and more.
Author-email: Sergej Winston <sergej.winston@bk.ru>
License: MIT
Requires-Dist: requests>=2.0.0
Requires-Dist: urllib3
